pyunit_map/__init__.py
pyunit_map/baidumap.py
pyunit_map/province.py
pyunit_map-2019.3.14.dist-info/METADATA
pyunit_map-2019.3.14.dist-info/WHEEL
pyunit_map-2019.3.14.dist-info/top_level.txt
pyunit_map-2019.3.14.dist-info/zip-safe
pyunit_map-2019.3.14.dist-info/RECORD
