Metadata-Version: 2.1
Name: pyunit-map
Version: 2019.3.14
Summary: 地图API接口
Home-page: https://github.com/PyUnit/pyunit-map
Author: Jtyoui
Author-email: jtyoui@qq.com
License: MIT Licence
Platform: any
Classifier: Programming Language :: Python :: 3
Classifier: License :: OSI Approved :: MIT License
Classifier: Operating System :: OS Independent
Requires-Dist: certifi (==2019.11.28)
Requires-Dist: chardet (==3.0.4)
Requires-Dist: et-xmlfile (==1.0.1)
Requires-Dist: idna (==2.8)
Requires-Dist: jdcal (==1.4.1)
Requires-Dist: numpy (==1.18.1)
Requires-Dist: openpyxl (==3.0.3)
Requires-Dist: pandas (==1.0.1)
Requires-Dist: python-dateutil (==2.8.1)
Requires-Dist: pytz (==2019.3)
Requires-Dist: requests (==2.22.0)
Requires-Dist: six (==1.14.0)
Requires-Dist: urllib3 (==1.25.8)
